mcp_feedback_collector/__init__.py
mcp_feedback_collector/server.py
mcp_server_feedback-2.1.0.dist-info/METADATA
mcp_server_feedback-2.1.0.dist-info/WHEEL
mcp_server_feedback-2.1.0.dist-info/entry_points.txt
mcp_server_feedback-2.1.0.dist-info/licenses/LICENSE
mcp_server_feedback-2.1.0.dist-info/RECORD
