Metadata-Version: 2.4
Name: mcp-server-feedback
Version: 2.1.0
Summary: A modern MCP server for interactive user feedback collection with GUI and Web modes
Project-URL: Homepage, https://github.com/sanshao85/mcp-server-feedback
Project-URL: Repository, https://github.com/sanshao85/mcp-server-feedback
Project-URL: Documentation, https://github.com/sanshao85/mcp-server-feedback#readme
Project-URL: Bug Tracker, https://github.com/sanshao85/mcp-server-feedback/issues
Author-email: MCP Server Feedback Team <feedback@example.com>
License: MIT
License-File: LICENSE
Keywords: ai-assistant,claude,feedback,gui,image-picker,interactive,mcp,model-context-protocol,server,web
Classifier: Development Status :: 4 - Beta
Classifier: Environment :: Console
Classifier: Environment :: MacOS X
Classifier: Environment :: Win32 (MS Windows)
Classifier: Environment :: X11 Applications
Classifier: Intended Audience :: Developers
Classifier: Intended Audience :: End Users/Desktop
Classifier: License :: OSI Approved :: MIT License
Classifier: Operating System :: OS Independent
Classifier: Programming Language :: Python :: 3
Classifier: Programming Language :: Python :: 3.8
Classifier: Programming Language :: Python :: 3.9
Classifier: Programming Language :: Python :: 3.10
Classifier: Programming Language :: Python :: 3.11
Classifier: Programming Language :: Python :: 3.12
Classifier: Topic :: Communications
Classifier: Topic :: Internet
Classifier: Topic :: Scientific/Engineering :: Artificial Intelligence
Classifier: Topic :: Software Development :: Libraries :: Python Modules
Classifier: Topic :: System :: Networking
Classifier: Topic :: Utilities
Requires-Python: >=3.8
Requires-Dist: flask>=2.0.0
Requires-Dist: mcp>=1.0.0
Requires-Dist: pillow>=8.0.0
Requires-Dist: psutil>=5.8.0
Requires-Dist: werkzeug>=2.0.0
Provides-Extra: dev
Requires-Dist: black; extra == 'dev'
Requires-Dist: isort; extra == 'dev'
Requires-Dist: mypy; extra == 'dev'
Requires-Dist: pytest>=6.0; extra == 'dev'
